training_hub/__init__.py
training_hub/_version.py
training_hub/hub_core.py
training_hub/utils.py
training_hub/algorithms/__init__.py
training_hub/algorithms/lora.py
training_hub/algorithms/osft.py
training_hub/algorithms/peft_extender.py
training_hub/algorithms/sft.py
training_hub/profiling/memory_estimator.py
training_hub-0.5.0.dist-info/licenses/LICENSE
training_hub-0.5.0.dist-info/METADATA
training_hub-0.5.0.dist-info/WHEEL
training_hub-0.5.0.dist-info/top_level.txt
training_hub-0.5.0.dist-info/RECORD
