Metadata-Version: 2.4
Name: training-hub
Version: 0.5.0
Summary: An algorithm-focused interface for common language model training, continual learning, and reinforcement learning techniques
License-Expression: Apache-2.0
Project-URL: homepage, https://ai-innovation.team/
Project-URL: source, https://github.com/Red-Hat-AI-Innovation-Team/training_hub
Project-URL: issues, https://github.com/Red-Hat-AI-Innovation-Team/training_hub/issues
Requires-Python: >=3.11
License-File: LICENSE
Requires-Dist: setuptools>=80.0
Requires-Dist: packaging>=24.2
Requires-Dist: wheel>=0.43
Requires-Dist: instructlab-training>=0.13.0
Requires-Dist: rhai-innovation-mini-trainer>=0.5.0
Requires-Dist: torch>=2.6.0
Requires-Dist: numba>=0.62.0
Requires-Dist: transformers>=4.57.0
Requires-Dist: datasets>=4.0.0
Requires-Dist: numpy>=1.26.4
Requires-Dist: rich>=14.1.0
Requires-Dist: peft>=0.15
Requires-Dist: pydantic>=2.7.0
Requires-Dist: aiofiles>=23.2.1
Requires-Dist: accelerate>=0.34.2
Requires-Dist: sympy>=1.0
Requires-Dist: networkx>=3.0
Requires-Dist: jinja2>=3.1.0
Requires-Dist: fsspec>=2025.0
Requires-Dist: pandas>=2.2
Requires-Dist: multiprocess>=0.70.16
Requires-Dist: aiohttp>=3.12
Requires-Dist: pyparsing>=3.0
Requires-Dist: regex>=2025.0
Requires-Dist: llvmlite>=0.42
Requires-Dist: filelock>=3.0
Requires-Dist: psutil>=6.0
Requires-Dist: urllib3>=2.4
Requires-Dist: frozenlist>=1.7
Requires-Dist: xxhash>=3.0
Requires-Dist: requests>=2.32.5
Requires-Dist: attr>=0.3.2
Requires-Dist: filelock>=3.19.1
Requires-Dist: mpmath>=1.3.0
Requires-Dist: pytest>=8.0
Provides-Extra: cuda
Requires-Dist: instructlab-training[cuda]>=0.13.0; extra == "cuda"
Requires-Dist: rhai-innovation-mini-trainer[cuda]>=0.5.0; extra == "cuda"
Requires-Dist: flash-attn>=2.8; extra == "cuda"
Requires-Dist: einops>=0.8; extra == "cuda"
Requires-Dist: kernels>=0.9.0; extra == "cuda"
Requires-Dist: bitsandbytes>=0.47.0; extra == "cuda"
Requires-Dist: liger-kernel>=0.5.10; extra == "cuda"
Requires-Dist: mamba-ssm[causal-conv1d]>=2.2.5; extra == "cuda"
Provides-Extra: lora
Requires-Dist: unsloth>=2025.10.11; extra == "lora"
Requires-Dist: trl>=0.18.0; extra == "lora"
Requires-Dist: xformers>=0.0.33.post1; extra == "lora"
Provides-Extra: dev
Requires-Dist: ipykernel; extra == "dev"
Requires-Dist: ipython; extra == "dev"
Dynamic: license-file
